BeijingTomorrow-0.1.0.dist-info/DESCRIPTION.rst
BeijingTomorrow-0.1.0.dist-info/METADATA
BeijingTomorrow-0.1.0.dist-info/RECORD
BeijingTomorrow-0.1.0.dist-info/WHEEL
BeijingTomorrow-0.1.0.dist-info/metadata.json
BeijingTomorrow-0.1.0.dist-info/top_level.txt
beijingtomorrow/__init__.py
beijingtomorrow/beijingpollutioncompiler.py
beijingtomorrow/databasebuilder.py
beijingtomorrow/image2lmdb.py
beijingtomorrow/pollutionlearner.py
beijingtomorrow/pollutionpredictor.py
beijingtomorrow/pollutionrflearner.py
beijingtomorrow/tilescraper.py
